simple_slack_bot/__init__.py
simple_slack_bot/simple_slack_bot.py
simple_slack_bot/slack_request.py
simple_slack_bot-2.3.4.dist-info/LICENSE.txt
simple_slack_bot-2.3.4.dist-info/METADATA
simple_slack_bot-2.3.4.dist-info/WHEEL
simple_slack_bot-2.3.4.dist-info/top_level.txt
simple_slack_bot-2.3.4.dist-info/RECORD
