Metadata-Version: 2.1
Name: simple-slack-bot
Version: 2.3.4
Summary: Simple Slack Bot makes writing your next Slack bot incredibly easy
Home-page: https://github.com/GregHilston/Simple-Slack-Bot
Author: Greg Hilston
Author-email: Gregory.Hilston@gmail.com
License: MIT
Download-URL: https://github.com/GregHilston/Simple-Slack-Bot/tarball/v2.3.4
Keywords: slack,bot,chat,simple
Platform: UNKNOWN
Requires-Python: >=3.7
Requires-Dist: pyyaml
Requires-Dist: slackclient (==2.8.0)
Requires-Dist: slacker (==0.14.0)
Requires-Dist: slacksocket (==1.0.1)
Requires-Dist: websocket-client (==0.56)
Requires-Dist: wheel
